dailyrevenue/__init__.py
dailyrevenue/dailyrevenue.py
testingpackagedavid-1.0.dist-info/METADATA
testingpackagedavid-1.0.dist-info/WHEEL
testingpackagedavid-1.0.dist-info/top_level.txt
testingpackagedavid-1.0.dist-info/RECORD
