Metadata-Version: 2.1
Name: testingpackagedavid
Version: 1.0
Summary: UNKNOWN
Home-page: UNKNOWN
Author: David Graafland
Author-email: david.graafland@gmail.com
License: UNKNOWN
Platform: UNKNOWN
Requires-Dist: pandas
